[ {
    "nom": "Dahl de lentilles corail",
    "temps": "10",
    "budget": "Prix malin",
    "energie": "Efficace",
    "saison": "hiver",
    "est_local": true,
    "organisation": "Zero gachis",
    "regime": ["Végétalien", "Végétarien", "Remise en forme"],
    "allergènes": [],
    "restrictions": ["Halal", "Sans porc", "Kasher"]
  },
  {
    "nom": "Omelette aux fines herbes",
    "temps": "10",
    "budget": "Prix malin",
    "energie": "Energie Zéro",
    "saison": "printemps",
    "est_local": true,
    "organisation": "Zero gachis",
    "regime": ["Végétarien", "Sportif"],
    "allergènes": ["Oeufs"],
    "restrictions": ["Halal", "Sans porc", "Kasher"]
  },
  {
    "nom": "Burger Boeuf & Cheddar",
    "temps": "20",
    "budget": "Petit plaisir",
    "energie": "Chef cuistot",
    "saison": "toutes",
    "est_local": false,
    "organisation": "Famille nombreuse",
    "regime": ["Gourmand"],
    "allergènes": ["Gluten", "Lait"],
    "restrictions": ["Sans porc"]
  },
  {
    "nom": "Wok de Tofu au Soja",
    "temps": "15",
    "budget": "Prix malin",
    "energie": "Efficace",
    "saison": "toutes",
    "est_local": false,
    "organisation": "Zero gachis",
    "regime": ["Végétalien", "Végétarien"],
    "allergènes": ["Soja"],
    "restrictions": ["Halal", "Sans porc", "Kasher"]
  },
  {
    "nom": "Salade de Pois Chiches",
    "temps": "10",
    "budget": "Prix malin",
    "energie": "Energie Zéro",
    "saison": "été",
    "est_local": true,
    "organisation": "Zero gachis",
    "regime": ["Végétalien", "Végétarien", "Remise en forme"],
    "allergènes": [],
    "restrictions": ["Halal", "Sans porc", "Kasher"]
  },
  {
    "nom": "Gratin de Pâtes au Jambon",
    "temps": "25",
    "budget": "Prix malin",
    "energie": "Chef cuistot",
    "saison": "hiver",
    "est_local": false,
    "organisation": "Famille nombreuse",
    "regime": ["Gourmand"],
    "allergènes": ["Gluten", "Lait"],
    "restrictions": []
  },
  {
    "nom": "Poisson Vapeur & Riz",
    "temps": "20",
    "budget": "Petit plaisir",
    "energie": "Efficace",
    "saison": "toutes",
    "est_local": true,
    "organisation": "Zero gachis",
    "regime": ["Sportif", "Remise en forme"],
    "allergènes": ["Poissons"],
    "restrictions": ["Halal", "Sans porc"]
  },
  {
    "nom": "Purée de Carottes Bébé",
    "temps": "20",
    "budget": "Prix malin",
    "energie": "Efficace",
    "saison": "automne",
    "est_local": true,
    "organisation": "Zero gachis",
    "regime": ["Bébé"],
    "allergènes": [],
    "restrictions": ["Halal", "Sans porc", "Kasher"]
  },
  {
    "nom": "Bowl Quinoa & Avocat",
    "temps": "10",
    "budget": "Petit plaisir",
    "energie": "Energie Zéro",
    "saison": "été",
    "est_local": false,
    "organisation": "Zero gachis",
    "regime": ["Végétarien", "Remise en forme"],
    "allergènes": [],
    "restrictions": ["Halal", "Sans porc", "Kasher"]
  },
  {
    "nom": "Poulet rôti du dimanche",
    "temps": "90",
    "budget": "Petit plaisir",
    "energie": "Chef cuistot",
    "saison": "toutes",
    "est_local": true,
    "organisation": "Famille nombreuse",
    "regime": ["Sportif", "Gourmand"],
    "allergènes": [],
    "restrictions": ["Halal", "Sans porc"]
  },
  {
    "nom": "Cookies aux Noisettes",
    "temps": "20",
    "budget": "Prix malin",
    "energie": "Chef cuistot",
    "saison": "toutes",
    "est_local": true,
    "organisation": "Zero gachis",
    "regime": ["Gourmand"],
    "allergènes": ["Gluten", "Fruits à coques", "Oeufs"],
    "restrictions": ["Kasher"]
  },
  {
    "nom": "Tartines de Chèvre Chaud",
    "temps": "10",
    "budget": "Prix malin",
    "energie": "Efficace",
    "saison": "printemps",
    "est_local": true,
    "organisation": "Zero gachis",
    "regime": ["Végétarien"],
    "allergènes": ["Gluten", "Lait"],
    "restrictions": ["Halal", "Sans porc"]
  },

  {
    "nom": "Velouté de Légumes d'Hiver",
    "temps": "20",
    "budget": "Prix malin",
    "energie": "Efficace",
    "saison": "hiver",
    "est_local": true,
    "organisation": "Zero gachis",
    "regime": ["Végétalien", "Végétarien", "Remise en forme"],
    "allergènes": [],
    "restrictions": ["Halal", "Sans porc", "Kasher"]
  },
  {
    "nom": "Salade de Lentilles & Feta",
    "temps": "10",
    "budget": "Prix malin",
    "energie": "Energie Zéro",
    "saison": "printemps",
    "est_local": true,
    "organisation": "Zero gachis",
    "regime": ["Végétarien", "Remise en forme"],
    "allergènes": ["Lait"],
    "restrictions": ["Sans porc"]
  },
  {
    "nom": "Tacos Poulet & Légumes",
    "temps": "20",
    "budget": "Petit plaisir",
    "energie": "Efficace",
    "saison": "toutes",
    "est_local": false,
    "organisation": "Famille nombreuse",
    "regime": ["Sportif", "Gourmand"],
    "allergènes": ["Gluten"],
    "restrictions": ["Sans porc", "Halal"]
  },
  {
    "nom": "Curry de Pois Chiches & Épinards",
    "temps": "20",
    "budget": "Prix malin",
    "energie": "Efficace",
    "saison": "hiver",
    "est_local": true,
    "organisation": "Zero gachis",
    "regime": ["Végétalien", "Végétarien"],
    "allergènes": [],
    "restrictions": ["Halal", "Sans porc", "Kasher"]
  },
  {
    "nom": "Pâtes Complètes aux Légumes Grillés",
    "temps": "20",
    "budget": "Prix malin",
    "energie": "Efficace",
    "saison": "été",
    "est_local": false,
    "organisation": "Famille nombreuse",
    "regime": ["Végétarien", "Remise en forme"],
    "allergènes": ["Gluten"],
    "restrictions": ["Halal", "Sans porc"]
  },
  {
    "nom": "Poêlée de Légumes d'Automne & Riz",
    "temps": "20",
    "budget": "Prix malin",
    "energie": "Efficace",
    "saison": "automne",
    "est_local": true,
    "organisation": "Zero gachis",
    "regime": ["Végétalien", "Végétarien"],
    "allergènes": [],
    "restrictions": ["Halal", "Sans porc", "Kasher"]
  },
  {
    "nom": "Galettes de Courgettes & Parmesan",
    "temps": "20",
    "budget": "Prix malin",
    "energie": "Chef cuistot",
    "saison": "été",
    "est_local": true,
    "organisation": "Zero gachis",
    "regime": ["Végétarien"],
    "allergènes": ["Lait", "Oeufs"],
    "restrictions": ["Sans porc"]
  },
  {
    "nom": "Chili Sin Carne",
    "temps": "30",
    "budget": "Prix malin",
    "energie": "Chef cuistot",
    "saison": "hiver",
    "est_local": false,
    "organisation": "Famille nombreuse",
    "regime": ["Végétalien", "Végétarien", "Gourmand"],
    "allergènes": [],
    "restrictions": ["Halal", "Sans porc", "Kasher"]
  },
  {
    "nom": "Filet de Saumon au Four & Légumes",
    "temps": "20",
    "budget": "Petit plaisir",
    "energie": "Efficace",
    "saison": "printemps",
    "est_local": false,
    "organisation": "Famille nombreuse",
    "regime": ["Sportif"],
    "allergènes": ["Poissons"],
    "restrictions": ["Sans porc"]
  },
  {
    "nom": "Wraps Végétariens Houmous & Crudités",
    "temps": "10",
    "budget": "Prix malin",
    "energie": "Energie Zéro",
    "saison": "été",
    "est_local": false,
    "organisation": "Zero gachis",
    "regime": ["Végétalien", "Végétarien", "Remise en forme"],
    "allergènes": ["Gluten", "Sésame"],
    "restrictions": ["Halal", "Sans porc", "Kasher"]
  },
  {
    "nom": "Ragoût de Bœuf & Carottes",
    "temps": "90",
    "budget": "Petit plaisir",
    "energie": "Chef cuistot",
    "saison": "hiver",
    "est_local": true,
    "organisation": "Famille nombreuse",
    "regime": ["Gourmand"],
    "allergènes": [],
    "restrictions": ["Sans porc", "Halal"]
  },
  {
    "nom": "Purée Patate Douce Bébé",
    "temps": "15",
    "budget": "Prix malin",
    "energie": "Efficace",
    "saison": "hiver",
    "est_local": true,
    "organisation": "Zero gachis",
    "regime": ["Bébé"],
    "allergènes": [],
    "restrictions": ["Halal", "Sans porc", "Kasher"]
  },
  {
    "nom": "Salade de Pâtes au Thon",
    "temps": "10",
    "budget": "Prix malin",
    "energie": "Energie Zéro",
    "saison": "été",
    "est_local": false,
    "organisation": "Famille nombreuse",
    "regime": ["Gourmand"],
    "allergènes": ["Gluten", "Poissons"],
    "restrictions": []
  },
  {
    "nom": "Poêlée de Gnocchis & Champignons",
    "temps": "15",
    "budget": "Petit plaisir",
    "energie": "Efficace",
    "saison": "automne",
    "est_local": false,
    "organisation": "Zero gachis",
    "regime": ["Végétarien", "Gourmand"],
    "allergènes": ["Gluten", "Lait"],
    "restrictions": []
  },
  {
    "nom": "Taboulé de Quinoa aux Herbes",
    "temps": "10",
    "budget": "Prix malin",
    "energie": "Energie Zéro",
    "saison": "été",
    "est_local": false,
    "organisation": "Zero gachis",
    "regime": ["Végétalien", "Végétarien", "Remise en forme"],
    "allergènes": [],
    "restrictions": ["Halal", "Sans porc", "Kasher"]
  },
  {
    "nom": "One-Pot Pasta Tomate & Basilic",
    "temps": "15",
    "budget": "Prix malin",
    "energie": "Efficace",
    "saison": "toutes",
    "est_local": false,
    "organisation": "Zero gachis",
    "regime": ["Végétarien"],
    "allergènes": ["Gluten"],
    "restrictions": ["Halal", "Sans porc"]
  },
  {
    "nom": "Buddha Bowl d'Hiver (Patate douce, Pois chiches, Chou kale)",
    "temps": "20",
    "budget": "Petit plaisir",
    "energie": "Chef cuistot",
    "saison": "hiver",
    "est_local": true,
    "organisation": "Zero gachis",
    "regime": ["Végétalien", "Végétarien", "Remise en forme"],
    "allergènes": [],
    "restrictions": ["Halal", "Sans porc", "Kasher"]
  },
  {
    "nom": "Risotto de Champignons d'Automne",
    "temps": "30",
    "budget": "Petit plaisir",
    "energie": "Chef cuistot",
    "saison": "automne",
    "est_local": true,
    "organisation": "Famille nombreuse",
    "regime": ["Végétarien", "Gourmand"],
    "allergènes": ["Lait"],
    "restrictions": ["Sans porc"]
  },
  {
    "nom": "Soupe Minestrone de Légumes",
    "temps": "20",
    "budget": "Prix malin",
    "energie": "Efficace",
    "saison": "hiver",
    "est_local": true,
    "organisation": "Zero gachis",
    "regime": ["Végétalien", "Végétarien", "Remise en forme"],
    "allergènes": [],
    "restrictions": ["Halal", "Sans porc", "Kasher"]
  },
  {
    "nom": "Pizza Maison Légumes du Soleil",
    "temps": "30",
    "budget": "Petit plaisir",
    "energie": "Chef cuistot",
    "saison": "été",
    "est_local": false,
    "organisation": "Famille nombreuse",
    "regime": ["Végétarien", "Gourmand"],
    "allergènes": ["Gluten", "Lait"],
    "restrictions": []
  },
  {
    "nom": "Salade Tiède Pommes de Terre & Haricots Verts",
    "temps": "20",
    "budget": "Prix malin",
    "energie": "Efficace",
    "saison": "été",
    "est_local": true,
    "organisation": "Zero gachis",
    "regime": ["Végétarien", "Remise en forme"],
    "allergènes": [],
    "restrictions": ["Halal", "Sans porc", "Kasher"]
  },
  {
    "nom": "Poulet Basquaise Express",
    "temps": "20",
    "budget": "Prix malin",
    "energie": "Efficace",
    "saison": "toutes",
    "est_local": false,
    "organisation": "Famille nombreuse",
    "regime": ["Sportif", "Gourmand"],
    "allergènes": [],
    "restrictions": ["Sans porc", "Halal"]
  },
  {
    "nom": "Tarte aux Légumes de Printemps",
    "temps": "30",
    "budget": "Prix malin",
    "energie": "Chef cuistot",
    "saison": "printemps",
    "est_local": true,
    "organisation": "Famille nombreuse",
    "regime": ["Végétarien"],
    "allergènes": ["Gluten", "Lait", "Oeufs"],
    "restrictions": []
  },
  {
    "nom": "Poêlée de Crevettes à l'Ail & Riz",
    "temps": "15",
    "budget": "Petit plaisir",
    "energie": "Efficace",
    "saison": "été",
    "est_local": false,
    "organisation": "Zero gachis",
    "regime": ["Sportif", "Gourmand"],
    "allergènes": ["Crustacés"],
    "restrictions": []
  },
  {
    "nom": "Gaufres Salées aux Épinards",
    "temps": "20",
    "budget": "Petit plaisir",
    "energie": "Chef cuistot",
    "saison": "hiver",
    "est_local": true,
    "organisation": "Famille nombreuse",
    "regime": ["Végétarien"],
    "allergènes": ["Gluten", "Lait", "Oeufs"],
    "restrictions": []
  },
  {
    "nom": "Bowl de Pois Cassés & Légumes Racines",
    "temps": "30",
    "budget": "Prix malin",
    "energie": "Chef cuistot",
    "saison": "hiver",
    "est_local": true,
    "organisation": "Zero gachis",
    "regime": ["Végétalien", "Végétarien", "Remise en forme"],
    "allergènes": [],
    "restrictions": ["Halal", "Sans porc", "Kasher"]
  },
  {
    "nom": "Croque-Monsieur Jambon & Fromage",
    "temps": "10",
    "budget": "Prix malin",
    "energie": "Energie Zéro",
    "saison": "toutes",
    "est_local": false,
    "organisation": "Famille nombreuse",
    "regime": ["Gourmand"],
    "allergènes": ["Gluten", "Lait"],
    "restrictions": []
  },
  {
    "nom": "Semoule aux Légumes du Couscous",
    "temps": "15",
    "budget": "Prix malin",
    "energie": "Efficace",
    "saison": "toutes",
    "est_local": true,
    "organisation": "Zero gachis",
    "regime": ["Végétalien", "Végétarien"],
    "allergènes": ["Gluten"],
    "restrictions": ["Halal", "Sans porc", "Kasher"]
  },
  {
    "nom": "Boulettes de Bœuf & Sauce Tomate",
    "temps": "20",
    "budget": "Prix malin",
    "energie": "Efficace",
    "saison": "toutes",
    "est_local": true,
    "organisation": "Famille nombreuse",
    "regime": ["Gourmand", "Sportif"],
    "allergènes": [],
    "restrictions": ["Sans porc", "Halal"]
  },
  {
    "nom": "Purée Courgette & Pomme de Terre Bébé",
    "temps": "15",
    "budget": "Prix malin",
    "energie": "Efficace",
    "saison": "été",
    "est_local": true,
    "organisation": "Zero gachis",
    "regime": ["Bébé"],
    "allergènes": [],
    "restrictions": ["Halal", "Sans porc", "Kasher"]
  },
  {
    "nom": "Salade de Riz Thon & Maïs",
    "temps": "10",
    "budget": "Prix malin",
    "energie": "Energie Zéro",
    "saison": "été",
    "est_local": false,
    "organisation": "Famille nombreuse",
    "regime": ["Gourmand"],
    "allergènes": ["Poissons"],
    "restrictions": []
  },
  {
    "nom": "Gratin de Courge & Pommes de Terre",
    "temps": "30",
    "budget": "Prix malin",
    "energie": "Chef cuistot",
    "saison": "automne",
    "est_local": true,
    "organisation": "Famille nombreuse",
    "regime": ["Végétarien", "Gourmand"],
    "allergènes": ["Lait"],
    "restrictions": []
  },
  {
    "nom": "Tofu Mariné & Nouilles Sautées",
    "temps": "20",
    "budget": "Petit plaisir",
    "energie": "Efficace",
    "saison": "toutes",
    "est_local": false,
    "organisation": "Zero gachis",
    "regime": ["Végétalien", "Végétarien", "Sportif"],
    "allergènes": ["Soja", "Gluten"],
    "restrictions": ["Halal", "Sans porc", "Kasher"]
  },
  {
    "nom": "Porridge Avoine & Fruits pour Bébé",
    "temps": "10",
    "budget": "Prix malin",
    "energie": "Energie Zéro",
    "saison": "toutes",
    "est_local": true,
    "organisation": "Zero gachis",
    "regime": ["Bébé"],
    "allergènes": ["Gluten"],
    "restrictions": ["Halal", "Sans porc", "Kasher"]
  },
  {
    "nom": "Quiche Poireaux & Lardons",
    "temps": "30",
    "budget": "Prix malin",
    "energie": "Chef cuistot",
    "saison": "hiver",
    "est_local": true,
    "organisation": "Famille nombreuse",
    "regime": ["Gourmand"],
    "allergènes": ["Gluten", "Lait", "Oeufs"],
    "restrictions": []
  },
  {
    "nom": "Salade d'Orge, Féta & Tomates",
    "temps": "20",
    "budget": "Petit plaisir",
    "energie": "Efficace",
    "saison": "été",
    "est_local": false,
    "organisation": "Zero gachis",
    "regime": ["Végétarien", "Remise en forme"],
    "allergènes": ["Gluten", "Lait"],
    "restrictions": []
  },
  {
    "nom": "Légumes Rôtis & Pois Chiches au Four",
    "temps": "30",
    "budget": "Prix malin",
    "energie": "Chef cuistot",
    "saison": "automne",
    "est_local": true,
    "organisation": "Zero gachis",
    "regime": ["Végétalien", "Végétarien", "Remise en forme"],
    "allergènes": [],
    "restrictions": ["Halal", "Sans porc", "Kasher"]
  },
  {
    "nom": "Gratin de Brocoli & Pâtes",
    "temps": "30",
    "budget": "Prix malin",
    "energie": "Chef cuistot",
    "saison": "hiver",
    "est_local": true,
    "organisation": "Famille nombreuse",
    "regime": ["Végétarien", "Gourmand"],
    "allergènes": ["Gluten", "Lait"],
    "restrictions": []
  },
  {
    "nom": "Bourguignon de Champignons",
    "temps": "30",
    "budget": "Petit plaisir",
    "energie": "Chef cuistot",
    "saison": "hiver",
    "est_local": true,
    "organisation": "Zero gachis",
    "regime": ["Végétalien", "Végétarien"],
    "allergènes": [],
    "restrictions": ["Halal", "Sans porc", "Kasher"]
  },
  {
    "nom": "Taboulé d'Hiver à la Courge",
    "temps": "20",
    "budget": "Prix malin",
    "energie": "Efficace",
    "saison": "automne",
    "est_local": true,
    "organisation": "Zero gachis",
    "regime": ["Végétalien", "Végétarien", "Remise en forme"],
    "allergènes": ["Gluten"],
    "restrictions": ["Halal", "Sans porc", "Kasher"]
  },
  {
    "nom": "Lasagnes Épinards & Ricotta",
    "temps": "30",
    "budget": "Petit plaisir",
    "energie": "Chef cuistot",
    "saison": "hiver",
    "est_local": false,
    "organisation": "Famille nombreuse",
    "regime": ["Végétarien", "Gourmand"],
    "allergènes": ["Gluten", "Lait"],
    "restrictions": []
  },
  {
    "nom": "Clafoutis de Légumes du Potager",
    "temps": "20",
    "budget": "Prix malin",
    "energie": "Chef cuistot",
    "saison": "printemps",
    "est_local": true,
    "organisation": "Zero gachis",
    "regime": ["Végétarien"],
    "allergènes": ["Lait", "Oeufs"],
    "restrictions": []
  },
  {
    "nom": "Salade d'Épeautre & Courge Rôtie",
    "temps": "20",
    "budget": "Petit plaisir",
    "energie": "Efficace",
    "saison": "automne",
    "est_local": true,
    "organisation": "Zero gachis",
    "regime": ["Végétarien", "Remise en forme"],
    "allergènes": ["Gluten"],
    "restrictions": []
  },
  {
    "nom": "Risotto de Printemps aux Asperges",
    "temps": "30",
    "budget": "Petit plaisir",
    "energie": "Chef cuistot",
    "saison": "printemps",
    "est_local": true,
    "organisation": "Famille nombreuse",
    "regime": ["Végétarien"],
    "allergènes": ["Lait"],
    "restrictions": []
  },
  {
    "nom": "Bowl Protéiné Lentilles & Patate Douce",
    "temps": "20",
    "budget": "Prix malin",
    "energie": "Efficace",
    "saison": "hiver",
    "est_local": true,
    "organisation": "Zero gachis",
    "regime": ["Végétalien", "Végétarien", "Sportif"],
    "allergènes": [],
    "restrictions": ["Halal", "Sans porc", "Kasher"]
  },
  {
    "nom": "Curry de Patate Douce & Pois Chiches",
    "temps": "20",
    "budget": "Prix malin",
    "energie": "Efficace",
    "saison": "automne",
    "est_local": true,
    "organisation": "Zero gachis",
    "regime": ["Végétalien", "Végétarien"],
    "allergènes": [],
    "restrictions": ["Halal", "Sans porc", "Kasher"]
  },
  {
    "nom": "Quinoa Sauce Basquaise",
    "temps": "20",
    "budget": "Prix malin",
    "energie": "Efficace",
    "saison": "toutes",
    "est_local": false,
    "organisation": "Zero gachis",
    "regime": ["Végétalien", "Végétarien", "Remise en forme"],
    "allergènes": [],
    "restrictions": ["Halal", "Sans porc", "Kasher"]
  },
  {
    "nom": "Papillotes de Poisson Blanc & Légumes",
    "temps": "20",
    "budget": "Petit plaisir",
    "energie": "Efficace",
    "saison": "printemps",
    "est_local": false,
    "organisation": "Famille nombreuse",
    "regime": ["Sportif", "Remise en forme"],
    "allergènes": ["Poissons"],
    "restrictions": ["Sans porc"]
  },
  {
    "nom": "Lasagnes de Légumes & Soja",
    "temps": "30",
    "budget": "Petit plaisir",
    "energie": "Chef cuistot",
    "saison": "hiver",
    "est_local": false,
    "organisation": "Famille nombreuse",
    "regime": ["Végétarien"],
    "allergènes": ["Gluten", "Lait", "Soja"],
    "restrictions": []
  },
  {
    "nom": "Poêlée de Riz au Fenouil & Herbes",
    "temps": "20",
    "budget": "Prix malin",
    "energie": "Efficace",
    "saison": "printemps",
    "est_local": true,
    "organisation": "Zero gachis",
    "regime": ["Végétalien", "Végétarien", "Remise en forme"],
    "allergènes": [],
    "restrictions": ["Halal", "Sans porc", "Kasher"]
  },
  {
    "nom": "Gratin de Potimarron & Chèvre",
    "temps": "30",
    "budget": "Petit plaisir",
    "energie": "Chef cuistot",
    "saison": "automne",
    "est_local": true,
    "organisation": "Famille nombreuse",
    "regime": ["Végétarien", "Gourmand"],
    "allergènes": ["Lait"],
    "restrictions": []
  },
  {
    "nom": "Pink Pasta Betterave & Ricotta",
    "temps": "15",
    "budget": "Petit plaisir",
    "energie": "Efficace",
    "saison": "hiver",
    "est_local": false,
    "organisation": "Zero gachis",
    "regime": ["Végétarien"],
    "allergènes": ["Gluten", "Lait"],
    "restrictions": []
  },
  {
    "nom": "Poivrons Farcis au Riz & Légumes",
    "temps": "30",
    "budget": "Prix malin",
    "energie": "Chef cuistot",
    "saison": "été",
    "est_local": true,
    "organisation": "Famille nombreuse",
    "regime": ["Végétalien", "Végétarien"],
    "allergènes": [],
    "restrictions": ["Halal", "Sans porc", "Kasher"]
  },
  {
    "nom": "Salade de Haricots Blancs & Avocat",
    "temps": "10",
    "budget": "Petit plaisir",
    "energie": "Energie Zéro",
    "saison": "été",
    "est_local": false,
    "organisation": "Zero gachis",
    "regime": ["Végétalien", "Végétarien", "Remise en forme", "Sportif"],
    "allergènes": [],
    "restrictions": ["Halal", "Sans porc", "Kasher"]
  },
  {
    "nom": "Œufs Brouillés Pain Complet & Fromage Blanc",
    "temps": "10",
    "budget": "Prix malin",
    "energie": "Energie Zéro",
    "saison": "toutes",
    "est_local": true,
    "organisation": "Zero gachis",
    "regime": ["Sportif", "Gourmand"],
    "allergènes": ["Oeufs", "Gluten", "Lait"],
    "restrictions": []
  },
  {
    "nom": "Purée Douce Carotte & Panais Bébé",
    "temps": "15",
    "budget": "Prix malin",
    "energie": "Efficace",
    "saison": "hiver",
    "est_local": true,
    "organisation": "Zero gachis",
    "regime": ["Bébé"],
    "allergènes": [],
    "restrictions": ["Halal", "Sans porc", "Kasher"]
  },
  {
    "nom": "Velouté Courgette & Petits Pois Bébé",
    "temps": "15",
    "budget": "Prix malin",
    "energie": "Efficace",
    "saison": "été",
    "est_local": true,
    "organisation": "Zero gachis",
    "regime": ["Bébé"],
    "allergènes": [],
    "restrictions": ["Halal", "Sans porc", "Kasher"]
  }
]

